edaplot/__init__.py
edaplot/api.py
edaplot/app_state.py
edaplot/data_prompts.py
edaplot/data_utils.py
edaplot/image_utils.py
edaplot/langsmith_utils.py
edaplot/llms.py
edaplot/paths.py
edaplot/prompt_utils.py
edaplot/py.typed
edaplot/spec_utils.py
edaplot/transform_utils.py
edaplot/vega.py
edaplot/recommend/__init__.py
edaplot/recommend/prompts.py
edaplot/recommend/recommender.py
edaplot/request_analyzer/__init__.py
edaplot/request_analyzer/header_analyzer.py
edaplot/request_analyzer/request_analyzer.py
edaplot/vega_chat/__init__.py
edaplot/vega_chat/prompts.py
edaplot/vega_chat/vega_chat.py
edaplot_vl-0.1.2.dist-info/METADATA
edaplot_vl-0.1.2.dist-info/WHEEL
edaplot_vl-0.1.2.dist-info/RECORD
