Metadata-Version: 2.4
Name: edaplot-vl
Version: 0.1.2
Summary: Plot your data with natural language
Classifier: Operating System :: OS Independent
Classifier: Programming Language :: Python :: 3
Requires-Python: >=3.10
Requires-Dist: altair[all]<6,>=5.5.0
Requires-Dist: commentjson<0.10,>=0.9.0
Requires-Dist: langchain-anthropic<0.4,>=0.3.13
Requires-Dist: langchain-ollama<0.4,>=0.3.10
Requires-Dist: langchain-openai<0.4,>=0.3.30
Requires-Dist: langchain<0.4,>=0.3.14
Requires-Dist: langgraph>=0.6.8
Requires-Dist: pandas<3,>=2.2.2
Requires-Dist: pillow<12,>=11.1.0
Requires-Dist: tqdm<5,>=4.67.1
Requires-Dist: vl-convert-python<2,>=1.7.0
